ej/__init__.py
ej-0.0.4.dist-info/LICENSE
ej-0.0.4.dist-info/METADATA
ej-0.0.4.dist-info/WHEEL
ej-0.0.4.dist-info/top_level.txt
ej-0.0.4.dist-info/RECORD
