Metadata-Version: 2.1
Name: ej
Version: 0.0.4
Summary: String generation
Home-page: https://github.com/thorwhalen/uu/tree/master/ej
Author: Thor Whalen
License: apache-2.0
Platform: any
License-File: LICENSE
